start/__init__.py
start/__main__.py
start/main.py
greptime_cloud_quick_start-1.0.2.dist-info/METADATA
greptime_cloud_quick_start-1.0.2.dist-info/WHEEL
greptime_cloud_quick_start-1.0.2.dist-info/entry_points.txt
greptime_cloud_quick_start-1.0.2.dist-info/licenses/LICENSE
greptime_cloud_quick_start-1.0.2.dist-info/RECORD
