Metadata-Version: 2.1
Name: greptime_cloud_quick_start
Version: 1.0.2
Summary: A quick start demo for GreptimeCloud
Project-URL: Homepage, https://github.com/GreptimeCloudStarters/quick-start-python
Project-URL: Bug Tracker, https://github.com/GreptimeCloudStarters/quick-start-python/issues
Author-email: CUI YIRAN <cuiyiran3@gmail.com>
License-File: LICENSE
Classifier: License :: OSI Approved :: Apache Software License
Classifier: Operating System :: OS Independent
Classifier: Programming Language :: Python :: 3
Requires-Python: >=3.10
Requires-Dist: opentelemetry-api==1.19.0
Requires-Dist: opentelemetry-exporter-otlp-proto-http==1.19.0
Requires-Dist: opentelemetry-instrumentation-system-metrics==0.40b0
Requires-Dist: opentelemetry-instrumentation==0.40b0
Requires-Dist: opentelemetry-proto==1.19.0
Requires-Dist: opentelemetry-sdk==1.19.0
